mlsocket/__init__.py
mlsocket/mlsocket.py
mlsocket-0.1.2.dist-info/AUTHORS.md
mlsocket-0.1.2.dist-info/LICENSE
mlsocket-0.1.2.dist-info/METADATA
mlsocket-0.1.2.dist-info/WHEEL
mlsocket-0.1.2.dist-info/top_level.txt
mlsocket-0.1.2.dist-info/RECORD
