Metadata-Version: 2.1
Name: mlsocket
Version: 0.1.2
Summary: Python socket for machine learning data
Home-page: https://github.com/k2sebeom/mlsocket
Author: SeBeom Lee
Author-email: moses97@gmail.com
License: MIT
Keywords: socket,ml,machine learning
Platform: UNKNOWN
Classifier: Natural Language :: English
Classifier: Intended Audience :: Developers
Classifier: Intended Audience :: Education
Classifier: Intended Audience :: Information Technology
Classifier: Intended Audience :: Science/Research
Classifier: Programming Language :: Python :: 3
Classifier: Programming Language :: Python :: 3.6
Classifier: Programming Language :: Python :: 3.7
Classifier: Programming Language :: Python :: 3.8
Classifier: License :: OSI Approved :: MIT License
Requires-Dist: numpy
Requires-Dist: h5py
Requires-Dist: joblib
